MANIFEST.in
README.md
requirements.txt
setup.cfg
setup.py
versioneer.py
botcity/plugins/twilio/sms/__init__.py
botcity/plugins/twilio/sms/_version.py
botcity/plugins/twilio/sms/plugin.py
botcity/plugins/twilio/sms/utils.py
botcity_twilio_sms_plugin.egg-info/PKG-INFO
botcity_twilio_sms_plugin.egg-info/SOURCES.txt
botcity_twilio_sms_plugin.egg-info/dependency_links.txt
botcity_twilio_sms_plugin.egg-info/requires.txt
botcity_twilio_sms_plugin.egg-info/top_level.txt