Metadata-Version: 2.1
Name: botcity-twilio-sms-plugin
Version: 0.1.2
Home-page: https://bitbucket.org/botcitydev/bot-twilio-sms-plugin-python.git
Requires-Python: >=3.7
